{"trial_id": "82476cd220c75c07f7e3c8ae84ee976b", "hyperparameters": {"space": [{"class_name": "Boolean", "config": {"name": "structured_data_block_1/normalize", "default": false, "conditions": []}}, {"class_name": "Boolean", "config": {"name": "structured_data_block_1/dense_block_1/use_batchnorm", "default": false, "conditions": []}}, {"class_name": "Choice", "config": {"name": "structured_data_block_1/dense_block_1/num_layers", "default": 2, "conditions": [], "values": [1, 2, 3], "ordered": true}}, {"class_name": "Choice", "config": {"name": "structured_data_block_1/dense_block_1/units_0", "default": 32, "conditions": [], "values": [16, 32, 64, 128, 256, 512, 1024], "ordered": true}}, {"class_name": "Choice", "config": {"name": "structured_data_block_1/dense_block_1/dropout", "default": 0.0, "conditions": [], "values": [0.0, 0.25, 0.5], "ordered": true}}, {"class_name": "Choice", "config": {"name": "structured_data_block_1/dense_block_1/units_1", "default": 32, "conditions": [], "values": [16, 32, 64, 128, 256, 512, 1024], "ordered": true}}, {"class_name": "Choice", "config": {"name": "classification_head_1/dropout", "default": 0, "conditions": [], "values": [0.0, 0.25, 0.5], "ordered": true}}, {"class_name": "Choice", "config": {"name": "optimizer", "default": "adam", "conditions": [], "values": ["adam", "sgd", "adam_weight_decay"], "ordered": false}}, {"class_name": "Choice", "config": {"name": "learning_rate", "default": 0.001, "conditions": [], "values": [0.1, 0.01, 0.001, 0.0001, 2e-05, 1e-05], "ordered": true}}, {"class_name": "Choice", "config": {"name": "structured_data_block_1/dense_block_1/units_2", "default": 32, "conditions": [], "values": [16, 32, 64, 128, 256, 512, 1024], "ordered": true}}], "values": {"structured_data_block_1/normalize": true, "structured_data_block_1/dense_block_1/use_batchnorm": false, "structured_data_block_1/dense_block_1/num_layers": 3, "structured_data_block_1/dense_block_1/units_0": 16, "structured_data_block_1/dense_block_1/dropout": 0, "structured_data_block_1/dense_block_1/units_1": 32, "classification_head_1/dropout": 0.25, "optimizer": "adam", "learning_rate": 0.001, "structured_data_block_1/dense_block_1/units_2": 256}}, "metrics": {"metrics": {"loss": {"direction": "min", "observations": [{"value": [0.035962387919425964], "step": 0}, {"value": [0.012911193072795868], "step": 1}, {"value": [0.010660304687917233], "step": 2}, {"value": [0.010074049234390259], "step": 3}, {"value": [0.009139113128185272], "step": 4}, {"value": [0.008762670680880547], "step": 5}, {"value": [0.008289851248264313], "step": 6}, {"value": [0.008080427534878254], "step": 7}, {"value": [0.0075862524099648], "step": 8}, {"value": [0.0076178559102118015], "step": 9}, {"value": [0.007574346382170916], "step": 10}, {"value": [0.006857225671410561], "step": 11}]}, "accuracy": {"direction": "max", "observations": [{"value": [0.9927289485931396], "step": 0}, {"value": [0.9972986578941345], "step": 1}, {"value": [0.9977746605873108], "step": 2}, {"value": [0.9977389574050903], "step": 3}, {"value": [0.9979888796806335], "step": 4}, {"value": [0.9980007410049438], "step": 5}, {"value": [0.9980840682983398], "step": 6}, {"value": [0.9981673359870911], "step": 7}, {"value": [0.9982149600982666], "step": 8}, {"value": [0.9982625842094421], "step": 9}, {"value": [0.9983339905738831], "step": 10}, {"value": [0.9984410405158997], "step": 11}]}, "val_loss": {"direction": "min", "observations": [{"value": [0.040040645748376846], "step": 0}, {"value": [0.03390800580382347], "step": 1}, {"value": [0.035022933036088943], "step": 2}, {"value": [0.03990352898836136], "step": 3}, {"value": [0.03911176323890686], "step": 4}, {"value": [0.04059472680091858], "step": 5}, {"value": [0.046591464430093765], "step": 6}, {"value": [0.04658198729157448], "step": 7}, {"value": [0.04501969739794731], "step": 8}, {"value": [0.04367993399500847], "step": 9}, {"value": [0.0375213623046875], "step": 10}, {"value": [0.0410197488963604], "step": 11}]}, "val_accuracy": {"direction": "max", "observations": [{"value": [0.9934185147285461], "step": 0}, {"value": [0.9943246841430664], "step": 1}, {"value": [0.9942770004272461], "step": 2}, {"value": [0.9943723678588867], "step": 3}, {"value": [0.9945631623268127], "step": 4}, {"value": [0.9957554340362549], "step": 5}, {"value": [0.9943723678588867], "step": 6}, {"value": [0.9938477873802185], "step": 7}, {"value": [0.9959462285041809], "step": 8}, {"value": [0.9954215884208679], "step": 9}, {"value": [0.9962800741195679], "step": 10}, {"value": [0.9962323307991028], "step": 11}]}}}, "score": 0.9962800741195679, "best_step": 10, "status": "COMPLETED"}