{"trial_id": "eb6e94839b5dd9a086b0f718db0ff336", "hyperparameters": {"space": [{"class_name": "Boolean", "config": {"name": "structured_data_block_1/normalize", "default": false, "conditions": []}}, {"class_name": "Boolean", "config": {"name": "structured_data_block_1/dense_block_1/use_batchnorm", "default": false, "conditions": []}}, {"class_name": "Choice", "config": {"name": "structured_data_block_1/dense_block_1/num_layers", "default": 2, "conditions": [], "values": [1, 2, 3], "ordered": true}}, {"class_name": "Choice", "config": {"name": "structured_data_block_1/dense_block_1/units_0", "default": 32, "conditions": [], "values": [16, 32, 64, 128, 256, 512, 1024], "ordered": true}}, {"class_name": "Choice", "config": {"name": "structured_data_block_1/dense_block_1/dropout", "default": 0.0, "conditions": [], "values": [0.0, 0.25, 0.5], "ordered": true}}, {"class_name": "Choice", "config": {"name": "structured_data_block_1/dense_block_1/units_1", "default": 32, "conditions": [], "values": [16, 32, 64, 128, 256, 512, 1024], "ordered": true}}, {"class_name": "Choice", "config": {"name": "classification_head_1/dropout", "default": 0, "conditions": [], "values": [0.0, 0.25, 0.5], "ordered": true}}, {"class_name": "Choice", "config": {"name": "optimizer", "default": "adam", "conditions": [], "values": ["adam", "sgd", "adam_weight_decay"], "ordered": false}}, {"class_name": "Choice", "config": {"name": "learning_rate", "default": 0.001, "conditions": [], "values": [0.1, 0.01, 0.001, 0.0001, 2e-05, 1e-05], "ordered": true}}, {"class_name": "Choice", "config": {"name": "structured_data_block_1/dense_block_1/units_2", "default": 32, "conditions": [], "values": [16, 32, 64, 128, 256, 512, 1024], "ordered": true}}], "values": {"structured_data_block_1/normalize": true, "structured_data_block_1/dense_block_1/use_batchnorm": false, "structured_data_block_1/dense_block_1/num_layers": 2, "structured_data_block_1/dense_block_1/units_0": 32, "structured_data_block_1/dense_block_1/dropout": 0, "structured_data_block_1/dense_block_1/units_1": 128, "classification_head_1/dropout": 0.0, "optimizer": "adam", "learning_rate": 0.001, "structured_data_block_1/dense_block_1/units_2": 256}}, "metrics": {"metrics": {"loss": {"direction": "min", "observations": [{"value": [0.04115079343318939], "step": 0}, {"value": [0.011901458725333214], "step": 1}, {"value": [0.0101855443790555], "step": 2}, {"value": [0.009379458613693714], "step": 3}, {"value": [0.00889750849455595], "step": 4}, {"value": [0.008618284948170185], "step": 5}, {"value": [0.008165583945810795], "step": 6}, {"value": [0.008017984218895435], "step": 7}, {"value": [0.007716128136962652], "step": 8}, {"value": [0.0076065221801400185], "step": 9}, {"value": [0.007504940032958984], "step": 10}]}, "accuracy": {"direction": "max", "observations": [{"value": [0.9891785979270935], "step": 0}, {"value": [0.9974464178085327], "step": 1}, {"value": [0.9978125095367432], "step": 2}, {"value": [0.9979642629623413], "step": 3}, {"value": [0.998035728931427], "step": 4}, {"value": [0.998160719871521], "step": 5}, {"value": [0.9981874823570251], "step": 6}, {"value": [0.9982410669326782], "step": 7}, {"value": [0.998285710811615], "step": 8}, {"value": [0.9983660578727722], "step": 9}, {"value": [0.9983303546905518], "step": 10}]}, "val_loss": {"direction": "min", "observations": [{"value": [0.04865207523107529], "step": 0}, {"value": [0.06175963953137398], "step": 1}, {"value": [0.061810463666915894], "step": 2}, {"value": [0.06462077796459198], "step": 3}, {"value": [0.07229073345661163], "step": 4}, {"value": [0.07972729206085205], "step": 5}, {"value": [0.08357974141836166], "step": 6}, {"value": [0.08966134488582611], "step": 7}, {"value": [0.09155573695898056], "step": 8}, {"value": [0.10593909025192261], "step": 9}, {"value": [0.10676279664039612], "step": 10}]}, "val_accuracy": {"direction": "max", "observations": [{"value": [0.9915357232093811], "step": 0}, {"value": [0.9917142987251282], "step": 1}, {"value": [0.9915714263916016], "step": 2}, {"value": [0.992821455001831], "step": 3}, {"value": [0.9928571581840515], "step": 4}, {"value": [0.9929642677307129], "step": 5}, {"value": [0.9926785826683044], "step": 6}, {"value": [0.9927499890327454], "step": 7}, {"value": [0.992821455001831], "step": 8}, {"value": [0.9927856922149658], "step": 9}, {"value": [0.9927142858505249], "step": 10}]}}}, "score": 0.9929642677307129, "best_step": 5, "status": "COMPLETED"}