{"trial_id": "d6897d63fc2cd9aa3f41c2c398944227", "hyperparameters": {"space": [{"class_name": "Boolean", "config": {"name": "structured_data_block_1/normalize", "default": false, "conditions": []}}, {"class_name": "Boolean", "config": {"name": "structured_data_block_1/dense_block_1/use_batchnorm", "default": false, "conditions": []}}, {"class_name": "Choice", "config": {"name": "structured_data_block_1/dense_block_1/num_layers", "default": 2, "conditions": [], "values": [1, 2, 3], "ordered": true}}, {"class_name": "Choice", "config": {"name": "structured_data_block_1/dense_block_1/units_0", "default": 32, "conditions": [], "values": [16, 32, 64, 128, 256, 512, 1024], "ordered": true}}, {"class_name": "Choice", "config": {"name": "structured_data_block_1/dense_block_1/dropout", "default": 0.0, "conditions": [], "values": [0.0, 0.25, 0.5], "ordered": true}}, {"class_name": "Choice", "config": {"name": "structured_data_block_1/dense_block_1/units_1", "default": 32, "conditions": [], "values": [16, 32, 64, 128, 256, 512, 1024], "ordered": true}}, {"class_name": "Choice", "config": {"name": "classification_head_1/dropout", "default": 0, "conditions": [], "values": [0.0, 0.25, 0.5], "ordered": true}}, {"class_name": "Choice", "config": {"name": "optimizer", "default": "adam", "conditions": [], "values": ["adam", "sgd", "adam_weight_decay"], "ordered": false}}, {"class_name": "Choice", "config": {"name": "learning_rate", "default": 0.001, "conditions": [], "values": [0.1, 0.01, 0.001, 0.0001, 2e-05, 1e-05], "ordered": true}}, {"class_name": "Choice", "config": {"name": "structured_data_block_1/dense_block_1/units_2", "default": 32, "conditions": [], "values": [16, 32, 64, 128, 256, 512, 1024], "ordered": true}}], "values": {"structured_data_block_1/normalize": true, "structured_data_block_1/dense_block_1/use_batchnorm": false, "structured_data_block_1/dense_block_1/num_layers": 3, "structured_data_block_1/dense_block_1/units_0": 32, "structured_data_block_1/dense_block_1/dropout": 0, "structured_data_block_1/dense_block_1/units_1": 32, "classification_head_1/dropout": 0.0, "optimizer": "adam", "learning_rate": 0.001, "structured_data_block_1/dense_block_1/units_2": 32}}, "metrics": {"metrics": {"loss": {"direction": "min", "observations": [{"value": [0.03659150004386902], "step": 0}, {"value": [0.01127170491963625], "step": 1}, {"value": [0.00971359945833683], "step": 2}, {"value": [0.009107405319809914], "step": 3}, {"value": [0.008532838895916939], "step": 4}, {"value": [0.008321712724864483], "step": 5}, {"value": [0.007854153402149677], "step": 6}, {"value": [0.0077045815996825695], "step": 7}, {"value": [0.007531133480370045], "step": 8}, {"value": [0.007371639367192984], "step": 9}, {"value": [0.007059894036501646], "step": 10}, {"value": [0.0070234499871730804], "step": 11}]}, "accuracy": {"direction": "max", "observations": [{"value": [0.9908124804496765], "step": 0}, {"value": [0.9976428747177124], "step": 1}, {"value": [0.9978749752044678], "step": 2}, {"value": [0.9980714321136475], "step": 3}, {"value": [0.9981428384780884], "step": 4}, {"value": [0.998160719871521], "step": 5}, {"value": [0.9982767701148987], "step": 6}, {"value": [0.9982946515083313], "step": 7}, {"value": [0.9983214139938354], "step": 8}, {"value": [0.9983839392662048], "step": 9}, {"value": [0.9984821677207947], "step": 10}, {"value": [0.9984375238418579], "step": 11}]}, "val_loss": {"direction": "min", "observations": [{"value": [0.04481196776032448], "step": 0}, {"value": [0.04210135340690613], "step": 1}, {"value": [0.04492556303739548], "step": 2}, {"value": [0.046845171600580215], "step": 3}, {"value": [0.047140639275312424], "step": 4}, {"value": [0.047712501138448715], "step": 5}, {"value": [0.04989221692085266], "step": 6}, {"value": [0.05189446732401848], "step": 7}, {"value": [0.04915298521518707], "step": 8}, {"value": [0.047004975378513336], "step": 9}, {"value": [0.05502950772643089], "step": 10}, {"value": [0.05006639286875725], "step": 11}]}, "val_accuracy": {"direction": "max", "observations": [{"value": [0.9927499890327454], "step": 0}, {"value": [0.9929642677307129], "step": 1}, {"value": [0.9934285879135132], "step": 2}, {"value": [0.993071436882019], "step": 3}, {"value": [0.993071436882019], "step": 4}, {"value": [0.992821455001831], "step": 5}, {"value": [0.9929642677307129], "step": 6}, {"value": [0.9929285645484924], "step": 7}, {"value": [0.9932857155799866], "step": 8}, {"value": [0.99314284324646], "step": 9}, {"value": [0.9933928847312927], "step": 10}, {"value": [0.993071436882019], "step": 11}]}}}, "score": 0.9934285879135132, "best_step": 2, "status": "COMPLETED"}